kobe/__init__.py
kobe/kobe_pb2.py
kobe/kobe_pb2_grpc.py
var/kobe/lib/ansible/plugins/callback/result.py
ansible_kobe_plugin-0.0.6.dist-info/LICENSE
ansible_kobe_plugin-0.0.6.dist-info/METADATA
ansible_kobe_plugin-0.0.6.dist-info/WHEEL
ansible_kobe_plugin-0.0.6.dist-info/top_level.txt
ansible_kobe_plugin-0.0.6.dist-info/RECORD
