Metadata-Version: 2.1
Name: ansible-kobe-plugin
Version: 0.0.6
Summary: A plugin for ansible to connect kobe
Home-page: UNKNOWN
Author: UNKNOWN
Author-email: UNKNOWN
License: MIT
Keywords: kobe
Platform: UNKNOWN
Requires-Dist: grpcio
Requires-Dist: grpcio-tools
Requires-Dist: ansible
